ckanext_jena-0.0.1-py2.7-nspkg.pth
ckanext/jena/__init__.py
ckanext/jena/backend.py
ckanext/jena/plugin.py
ckanext/jena/logic/__init__.py
ckanext/jena/logic/action.py
ckanext/jena/logic/auth.py
ckanext_jena-0.0.1.dist-info/LICENSE
ckanext_jena-0.0.1.dist-info/METADATA
ckanext_jena-0.0.1.dist-info/WHEEL
ckanext_jena-0.0.1.dist-info/entry_points.txt
ckanext_jena-0.0.1.dist-info/namespace_packages.txt
ckanext_jena-0.0.1.dist-info/top_level.txt
ckanext_jena-0.0.1.dist-info/RECORD
