Metadata-Version: 2.1
Name: ckanext-jena
Version: 0.0.1
Summary: An extension for storing file with Apache Jena
Home-page: https://github.com/etri-odp/ckanext-jena
Author: Chau Nguyen
Author-email: chau@etri.re.kr
License: AGPL
Keywords: CKAN
Platform: UNKNOWN
Classifier: Development Status :: 4 - Beta
Classifier: License :: OSI Approved :: GNU Affero General Public License v3 or later (AGPLv3+)
Classifier: Programming Language :: Python :: 2.7
